README
setup.py
packetEssentials/__init__.py
packetEssentials.egg-info/PKG-INFO
packetEssentials.egg-info/SOURCES.txt
packetEssentials.egg-info/dependency_links.txt
packetEssentials.egg-info/top_level.txt
packetEssentials/lib/__init__.py
packetEssentials/lib/chan_freq.py
packetEssentials/lib/converter.py
packetEssentials/lib/drivers.py
packetEssentials/lib/nic.py
packetEssentials/lib/subtypes.py
packetEssentials/lib/unifier.py
packetEssentials/lib/utils.py