Metadata-Version: 1.0
Name: packetEssentials
Version: 1.0.2
Summary: Essential nuances for Python Scapy revolving around packet hacking
Home-page: https://github.com/ICSec/packetEssentials
Author: stryngs
Author-email: info@ethicalreporting.org
License: GNU General Public License v2
Keywords: 802.11 wifi ether scapy packet essentials
Platform: UNKNOWN
